nerkit/HanLP.py
nerkit/StanfordCoreNLP.py
nerkit/StanzaApi.py
nerkit/__init__.py
nerkit/__pycache__/HanLP.cpython-36.pyc
nerkit/__pycache__/HanLP.cpython-39.pyc
nerkit/__pycache__/StanfordCoreNLP.cpython-36.pyc
nerkit/__pycache__/StanfordCoreNLP.cpython-39.pyc
nerkit/__pycache__/StanzaApi.cpython-39.pyc
nerkit/__pycache__/__init__.cpython-36.pyc
nerkit/__pycache__/__init__.cpython-39.pyc
nerkit/triples/__init__.py
nerkit/triples/ltp.py
nerkit/triples/patterns.py
nerkit/triples/sentence_parser.py
nerkit/triples/text.py
nerkit/triples/__pycache__/__init__.cpython-36.pyc
nerkit/triples/__pycache__/ltp.cpython-36.pyc
nerkit/triples/__pycache__/patterns.cpython-36.pyc
nerkit/triples/__pycache__/sentence_parser.cpython-36.pyc
nerkit/triples/__pycache__/text.cpython-36.pyc
ner_kit-0.0.5.dist-info/LICENSE
ner_kit-0.0.5.dist-info/METADATA
ner_kit-0.0.5.dist-info/WHEEL
ner_kit-0.0.5.dist-info/top_level.txt
ner_kit-0.0.5.dist-info/RECORD
