Metadata-Version: 2.1
Name: ner-kit
Version: 0.0.5
Summary: Named Entity Recognition Toolkit
Home-page: https://github.com/dhchenx/ner-kit
Author: Donghua Chen
Author-email: douglaschan@126.com
License: MIT
Project-URL: Bug Reports, https://github.com/dhchenx/ner-kit/issues
Project-URL: Source, https://github.com/dhchenx/ner-kit
Keywords: named entity recognition,NER,text analysis
Platform: UNKNOWN
Classifier: Development Status :: 5 - Production/Stable
Classifier: Intended Audience :: Developers
Classifier: Topic :: Software Development :: Build Tools
Classifier: License :: OSI Approved :: MIT License
Classifier: Programming Language :: Python :: 3
Classifier: Programming Language :: Python :: 3.6
Classifier: Programming Language :: Python :: 3.7
Classifier: Programming Language :: Python :: 3.8
Classifier: Programming Language :: Python :: 3.9
Classifier: Programming Language :: Python :: 3 :: Only
Requires-Python: >=3.6, <4
Requires-Dist: stanfordcorenlp
Requires-Dist: stanza
Requires-Dist: tqdm
Requires-Dist: quick-crawler
Requires-Dist: networkx
Requires-Dist: pandas
Requires-Dist: matplotlib
Provides-Extra: dev
Requires-Dist: check-manifest ; extra == 'dev'
Provides-Extra: test
Requires-Dist: coverage ; extra == 'test'
